rsdict/__init__.py
rsdict/rsdict.py
rsdict-0.1.8.dist-info/LICENSE
rsdict-0.1.8.dist-info/METADATA
rsdict-0.1.8.dist-info/WHEEL
rsdict-0.1.8.dist-info/top_level.txt
rsdict-0.1.8.dist-info/RECORD
