Metadata-Version: 2.1
Name: rsdict
Version: 0.1.8
Summary: Type or key restricted and resettable dictionary
Home-page: https://github.com/kihiyuki/python-rsdict
Author: kihiyuki
Author-email: kihiyuki.11@gmail.com
License: MIT License
Platform: UNKNOWN
Classifier: License :: OSI Approved :: MIT License
Classifier: Programming Language :: Python :: 3
Classifier: Programming Language :: Python :: 3.5
Classifier: Programming Language :: Python :: 3.6
Classifier: Programming Language :: Python :: 3.7
Classifier: Programming Language :: Python :: 3.8
Classifier: Programming Language :: Python :: 3.9
Requires-Python: >=3.5
License-File: LICENSE
